VODet/__init__.py
VODet/__main__.py
VODet/analyzer.py
VODet/chat.py
VODet/config.json
VODet/helixClient.py
VODet/logger.py
VODet/parameters.py
VODet/sample-config.json
VODet/settings.py
VODet/stringUtil.py
VODet/.vscode/settings.json
VODet/plots/README.txt
VODet-0.0.2.6.dist-info/LICENSE.txt
VODet-0.0.2.6.dist-info/METADATA
VODet-0.0.2.6.dist-info/WHEEL
VODet-0.0.2.6.dist-info/entry_points.txt
VODet-0.0.2.6.dist-info/top_level.txt
VODet-0.0.2.6.dist-info/RECORD
